<string_table>

	<string id="st_wpn_beretta_stars">
		<text>Beretta 92F "Звёзды"</text>
	</string>
	<string id="st_wpn_beretta_stars_descr">
		<text>Beretta 92F - это, пожалуй, самый известный пистолет американских военных, который пришёл на смену легендарному М1911. Характерными особенностями данного пистолета являются: схема автоматики с использованием энергии отдачи при коротком ходе ствола, выполненная из алюминиевого сплава рамка и хромированный канал ствола. Оружие пользуется большой популярностью и принято на вооружение несколькими странами мира.\n \n
		%c[ui_gray_2]НАВЕСНОЕ ОБОРУДОВАНИЕ: \n
		%c[d_purple] • %c[ui_gray_2] глушитель 9 мм (после модификации)\n
		%c[d_purple] • %c[ui_gray_2] Прицелы: Docter, RMR, DeltaPoint \n \n</text>
	</string>
</string_table>
